nd2/__init__.py
nd2/_binary.py
nd2/_ome.py
nd2/_sdk_types.py
nd2/_util.py
nd2/index.py
nd2/nd2file.py
nd2/py.typed
nd2/structures.py
nd2/tiff.py
nd2/_parse/__init__.py
nd2/_parse/_chunk_decode.py
nd2/_parse/_clx_lite.py
nd2/_parse/_clx_xml.py
nd2/_parse/_legacy_xml.py
nd2/_parse/_parse.py
nd2/readers/__init__.py
nd2/readers/protocol.py
nd2/readers/_legacy/__init__.py
nd2/readers/_legacy/legacy_reader.py
nd2/readers/_modern/__init__.py
nd2/readers/_modern/modern_reader.py
nd2-0.10.2.dist-info/METADATA
nd2-0.10.2.dist-info/WHEEL
nd2-0.10.2.dist-info/licenses/LICENSE
nd2-0.10.2.dist-info/RECORD
