Metadata-Version: 2.4
Name: nd2
Version: 0.10.2
Summary: Yet another nd2 (Nikon NIS Elements) file reader
Project-URL: homepage, https://github.com/tlambert03/nd2
Project-URL: repository, https://github.com/tlambert03/nd2
Project-URL: changelog, https://github.com/tlambert03/nd2/blob/main/CHANGELOG.md
Project-URL: documentation, https://tlambert03.github.io/nd2/
Author-email: Talley Lambert <talley.lambert@gmail.com>
License: BSD 3-Clause License
License-File: LICENSE
Classifier: Development Status :: 4 - Beta
Classifier: License :: OSI Approved :: BSD License
Classifier: Programming Language :: Python :: 3
Classifier: Programming Language :: Python :: 3.8
Classifier: Programming Language :: Python :: 3.9
Classifier: Programming Language :: Python :: 3.10
Classifier: Programming Language :: Python :: 3.11
Classifier: Programming Language :: Python :: 3.12
Requires-Python: >=3.8
Requires-Dist: numpy
Requires-Dist: ome-types>=0.5.1
Requires-Dist: resource-backed-dask-array
Requires-Dist: typing-extensions
Provides-Extra: dev
Requires-Dist: aicsimageio; extra == 'dev'
Requires-Dist: dask[array]; extra == 'dev'
Requires-Dist: imagecodecs; extra == 'dev'
Requires-Dist: ipython; extra == 'dev'
Requires-Dist: lxml; (python_version >= '3.9') and extra == 'dev'
Requires-Dist: mypy; extra == 'dev'
Requires-Dist: numpy; extra == 'dev'
Requires-Dist: pre-commit; extra == 'dev'
Requires-Dist: psutil; extra == 'dev'
Requires-Dist: pytest-codspeed; extra == 'dev'
Requires-Dist: pytest-cov; extra == 'dev'
Requires-Dist: pytest-pretty; extra == 'dev'
Requires-Dist: pytest>=6.0; extra == 'dev'
Requires-Dist: rich; extra == 'dev'
Requires-Dist: ruff; extra == 'dev'
Requires-Dist: tifffile; extra == 'dev'
Requires-Dist: types-lxml; extra == 'dev'
Requires-Dist: xarray; extra == 'dev'
Provides-Extra: docs
Requires-Dist: mkdocs; extra == 'docs'
Requires-Dist: mkdocs-material; extra == 'docs'
Requires-Dist: mkdocstrings-python; extra == 'docs'
Provides-Extra: legacy
Requires-Dist: imagecodecs; extra == 'legacy'
Provides-Extra: test
Requires-Dist: aicsimageio; extra == 'test'
Requires-Dist: dask[array]; extra == 'test'
Requires-Dist: imagecodecs; extra == 'test'
Requires-Dist: lxml; (python_version >= '3.9') and extra == 'test'
Requires-Dist: numpy; extra == 'test'
Requires-Dist: psutil; extra == 'test'
Requires-Dist: pytest-codspeed; extra == 'test'
Requires-Dist: pytest-cov; extra == 'test'
Requires-Dist: pytest-pretty; extra == 'test'
Requires-Dist: pytest>=6.0; extra == 'test'
Requires-Dist: tifffile; extra == 'test'
Requires-Dist: xarray; extra == 'test'
Provides-Extra: tiff
Requires-Dist: tifffile; extra == 'tiff'
